{
  "date": "2026-07-13",
  "updateTime": "11:40",
  "weekDay": "星期一",
  "modules": [
    {
      "id": 1,
      "name": "AGV仓储/物流新闻",
      "count": 8,
      "hasNews": true,
      "items": [
        {
          "title": "顺丰与New Balance合建上海智慧交付中心正式启幕",
          "source": "新浪微博",
          "time": "2026-07-09",
          "url": "https://weibo.com/3215082647/5319433335346702",
          "summary": "顺丰集团与New Balance联合打造的中国智慧交付中心在上海正式启幕，配备料箱机器人货到人系统、高速穿梭车式立库、环形交叉带分拣系统、闪电播种墙及自动打包机等自动化设备，形成千万级库容，单日出库峰值约37万件。存储能力提升160%，B2B出库能力提升60%，电商出库效率提升50%。",
          "tags": ["智慧交付中心", "顺丰", "AGV", "自动化仓储"]
        },
        {
          "title": "铁建重工申请AGV参数标定专利，实现快速精准标定",
          "source": "新浪财经",
          "time": "2026-07-11",
          "url": "https://www.toutiao.com/article/7661085019074609716/",
          "summary": "中国铁建重工集团申请AGV参数标定专利(CN122363076A)，通过自动化采集姿态角差值和偏差距离，自动优化舵轮角度偏置值和零位偏置系数，替代人工标定流程，缩短标定周期，精准可控。铁建重工总部位于湖南长沙。",
          "tags": ["AGV", "专利", "铁建重工", "参数标定"]
        },
        {
          "title": "佑驾创新发布Combo全链路无人物流方案，四轮足机器人亮相",
          "source": "36氪",
          "time": "2026-07-06",
          "url": "https://www.xiouwang.cn/webnews/3728.html",
          "summary": "佑驾创新正式发布Combo全链路无人物流闭环方案，旗下曜行动力打造的四轮足式机器人同步亮相。该方案旨在打通物流全链条无人化作业，四轮足式机器人融合轮式与足式运动优势，可应用于仓储、园区等场景的物资转运。",
          "tags": ["无人物流", "四轮足机器人", "佑驾创新"]
        },
        {
          "title": "Link Mart中国区智能仓储基地在合肥正式启动建设",
          "source": "中华网",
          "time": "2026-07-09",
          "url": "https://life.china.com/2026-07/11/content_601061.html",
          "summary": "7月9日Link Mart中国区智能仓储基地在合肥奠基，规划建设智能立体仓储中心、物流分拨中心、数字运营中心等核心板块。项目全面采用WMS、自动化立体仓库、AGV智能搬运机器人、自动分拣系统、AI调度平台等，实现仓储管理全过程数字化。",
          "tags": ["智能仓储", "AGV", "WMS"]
        },
        {
          "title": "咸宁高新区启动安利5G-AGV智能转运项目",
          "source": "搜狐科技",
          "time": "2026-07-09",
          "url": "https://www.sohu.com/a/1047801566_122066678",
          "summary": "安利大健康智创园5G-AGV智能转运项目在咸宁高新区正式启动。作为安利全球唯一的汉本萃中草药产品供应基地，该系统依托5G网络实现物料全自动转运，有效减少人工操作误差、降低生产损耗，提升物料周转效率与生产标准化水平。",
          "tags": ["5G-AGV", "智能转运", "安利"]
        },
        {
          "title": "海康机器人20万台AMR下线，中国物流自动化跨越分水岭",
          "source": "今日头条/物流沙龙",
          "time": "2026-07-06",
          "url": "https://www.toutiao.com/article/7659357991765901866",
          "summary": "海康机器人桐庐科技园第20万台移动机器人下线，第一个10万台用了八年，第二个10万台仅用两年。标志着中国物流机器人行业从探索性应用走向规模化普及，AMR类产品占比已超过60%。",
          "tags": ["AMR", "海康机器人", "规模化"]
        },
        {
          "title": "林德自动化AI智能库+平衡重式机器人破解酒业物流困局",
          "source": "腾讯新闻",
          "time": "2026-07-08",
          "url": "https://new.qq.com/rain/a/20260708A07NO100",
          "summary": "林德自动化携AI智能库与平衡重式机器人E-MATIC亮相酒类物流年会，融合叉式AGV、四向穿梭车、智能调度系统等核心技术，打造原料入库-生产转运-仓储存储-出库配送全链路柔性自动化方案。",
          "tags": ["AGV", "智能仓储", "酒业物流"]
        },
        {
          "title": "2026年智能物流搬运车市场深度分析：AMR成为主流选择",
          "source": "海玛智能/行业分析",
          "time": "2026-07",
          "url": "https://www.hepan.com/article-611136-1.html",
          "summary": "全球移动机器人市场规模预计2026年突破450亿美元，CAGR23%以上。中国智能物流搬运车出货量占全球超40%。2025-2026年国内新增智能搬运设备中AMR占比超60%，制造业一线普工年均成本突破9万元。",
          "tags": ["AMR", "市场分析", "智能物流"]
        }
      ]
    },
    {
      "id": 2,
      "name": "长沙岳麓区招聘动态",
      "count": 11,
      "hasNews": true,
      "items": [
        {
          "title": "TMS/WMS/LES/WCS方向产品经理",
          "salary": "15-20k",
          "company": "中科云谷",
          "url": "https://m.liepin.com/job/1964217707.shtml",
          "tags": ["WMS", "产品经理", "岳麓区"],
          "desc": "长沙-岳麓区，3-5年经验，统招本科。要求有TMS/WMS/LES/WCS开发或实施经验，熟悉制造业物流情况，懂工业工程优先。中联重科旗下工业互联网公司。"
        },
        {
          "title": "WMS项目经理",
          "salary": "13-17k·15薪",
          "company": "中科云谷",
          "url": "https://m.liepin.com/job/1964379665.shtml",
          "tags": ["WMS", "项目经理", "望城区"],
          "desc": "长沙-望城区，5年以上经验，本科。熟悉供应链管理或仓储物流业务流程体系及前沿技术，对WMS仓储管理系统、厂内物流LES有实际实施落地经验，通过PMP认证者优先。"
        },
        {
          "title": "项目经理(长沙)",
          "salary": "1.4-1.6万/月",
          "company": "中机国际",
          "url": "https://www.yupao.com/qiye/1846144085979697165.html",
          "tags": ["项目经理", "长沙", "国企"],
          "desc": "建筑项目经理，国企(国机集团旗下)，9险2金+双休+带薪年假。公司负2层直通长沙地铁3号线东塘站。目前有28个在招职位。"
        },
        {
          "title": "产品经理(水利工程产品信息化)",
          "salary": "10-20k",
          "company": "博识峰云",
          "url": "https://bebee.com/cn/jobs/job--techmap_cn_83465797",
          "tags": ["产品经理", "岳麓区-王家湾", "WLB优"],
          "desc": "长沙-岳麓区王家湾，3-5年经验。9:30-18:30双休+午休1.5小时，六险一金+带薪年假+13-15薪奖金+股权激励。专精特新企业+华为鲲鹏认证。水利项目管理平台产品经理。"
        },
        {
          "title": "产品经理(湿法设备)",
          "salary": "10-15k",
          "company": "湖南红太阳光电",
          "url": "http://job.jdzj.com/job3176042.shtml",
          "tags": ["产品经理", "湘江新区", "半导体光伏"],
          "desc": "长沙湘江新区(岳麓区)，应届毕业生可投，本科。湿法清洗设备开发规划、总体设计及产业化推广。熟悉光伏电池(TOPCON/XBC/HJT)湿法制绒清洗工艺。"
        },
        {
          "title": "项目经理(仓储/AGV/堆垛机方向)",
          "salary": "1-1.5万",
          "company": "弗兰度智能科技(长沙)",
          "url": "https://www.zhaopin.com/jobdetail/CCL1466111080J40891519315.htm",
          "tags": ["项目经理", "仓储物流", "AGV"],
          "desc": "长沙-望城区，3-5年经验，本科。PMP+系统集成项目管理工程师。熟悉AGV、堆垛机、仓储项目、工业自动化。弗兰度是意大利技术在长沙的子公司，5万平米生产基地。"
        },
        {
          "title": "鸿蒙硬件产品经理",
          "salary": "15-25k",
          "company": "拓维信息",
          "url": "https://m.liepin.com/job/1983044989.shtml",
          "tags": ["产品经理", "岳麓区", "鸿蒙"],
          "desc": "长沙-岳麓区，3-10年经验，统招本科。负责开源鸿蒙行业组件的产品规划、Roadmap制定及架构设计，推进智慧城市与交通控制领域落地。"
        },
        {
          "title": "AI应用产品经理",
          "salary": "15-25k",
          "company": "拓维信息",
          "url": "https://m.liepin.com/job/1983265541.shtml",
          "tags": ["产品经理", "岳麓区", "AI"],
          "desc": "长沙-岳麓区，3年以上经验，统招本科。负责基于开源鸿蒙的AI应用产品全生命周期管理，包括智能家居、工业IoT、教育设备等场景。"
        },
        {
          "title": "产线技术专家",
          "salary": "1.5-3万·14薪",
          "company": "湖南航天环宇通信科技股份",
          "url": "https://www.zhaopin.com/jobdetail/CC238591710J40915357815.htm",
          "tags": ["技术专家", "岳麓区", "航空航天"],
          "desc": "长沙-岳麓区，5-10年经验，硕士。复材制件成型或飞机部装自动化产线业务技术管理。已上市(688523)，900余人。另有研发类20-60万/年多个岗位在招。"
        },
        {
          "title": "技术支持/维护(仓储物流软件方向)",
          "salary": "6-9k",
          "company": "亦典科技",
          "url": "https://www.qcc.com/jobdetail/ce631224f3c8c2db3160543636652842.html",
          "tags": ["技术支持", "岳麓区-麓谷", "WLB优"],
          "desc": "长沙-岳麓区麓谷，经验不限。亦典科技(海典软件子公司)提供现代化仓储物流全面解决方案。福利：7小时工作制(9:00-12:00+1:30-5:30)双休、五险一金、年中年末集体旅游、生日Party。"
        },
        {
          "title": "经营业务岗(长沙)",
          "salary": "央企待遇",
          "company": "中国物流集团",
          "url": "https://chinalogisticsgroup.hotjob.cn/SU6426c1e1bef57c1e26962897/pb/posDetail.html",
          "tags": ["经营业务", "长沙", "央企"],
          "desc": "长沙市，协助项目负责人开展业务执行工作，做好客户开发与维护。中国物流集团为国资委直管央企，六险二金，本科综合年薪12-18万。"
        }
      ]
    },
    {
      "id": 3,
      "name": "岳麓区实验小学东校区通知",
      "count": 0,
      "hasNews": false,
      "items": []
    },
    {
      "id": 4,
      "name": "少数民族运动会征集结果",
      "count": 1,
      "hasNews": true,
      "items": [
        {
          "title": "征集已截止(7月10日17:00)，评选结果尚未公布",
          "content": "第十三届全国少数民族传统体育运动会主题口号/会徽/吉祥物/主题歌/宣传画征集已于2026年7月10日17:00截止。目前评选结果尚未公布，预计评审后将在官方渠道公布获奖名单。运动会将于2027年在湘西州和张家界举行。"
        }
      ]
    },
    {
      "id": 5,
      "name": "梅溪湖晟通施工进度",
      "count": 4,
      "hasNews": true,
      "items": [
        {
          "title": "长沙旺旺棒球俱乐部落户梅溪湖国际新城",
          "content": "7月6日，长沙旺旺棒球俱乐部正式落户梅溪湖国际新城二期，以梅溪湖作为未来主场，征战中国棒球城市联赛(CPB)。这是华中地区首支职业棒球队，由旺旺集团全资设立，将推动棒球运动在长沙规模化普及。"
        },
        {
          "title": "象鼻窝森林公园森林生态步道全面建成",
          "content": "长沙象鼻窝森林公园森林生态步道已全面建成，园内应急防灾配套设施工程进入攻坚阶段。公园位于梅溪湖国际新城二期，总规划面积约5172.3亩，森林覆盖率85.35%。目前全域处于全封闭施工状态，待正式建成开放后再前往游览。"
        },
        {
          "title": "地铁2号线西延二期完成安全预评估，梅溪湖西段预计8月底先行运营",
          "content": "7月2日消息，长沙地铁2号线西延二期工程顺利完成初期运营前安全预评估，计划先期开通龙虎岭站至梅溪湖西站区段，最快8月底前分段开通。工程起于梅溪湖西站，止于长沙火车西站，全长约13.82公里，共设站11座。"
        },
        {
          "title": "长沙市口腔医院梅溪湖新院7月24日全面启动接诊",
          "content": "长沙市口腔医院梅溪湖新院官宣定档7月24日全面启动接诊。医院位于梅溪湖核心一期，总建筑面积14.6万㎡，总投资近10亿元，规划500张专业牙椅，首批开放274张。这是河西首家大型三甲口腔专科医院。"
        }
      ]
    }
  ]
}
